{
  "BotId": 15,
  "Bubbles": [
    {
      "id": 0,
      "text": "Hi! 😃",
      "responseType": 0,
      "mediaUrl": "",
      "optionsCount": 0,
      "isEntryPointForNewTest": false,
      "questionsCount": 0,
      "filename": "",
      "nextBubbleId": 1,
      "delay": 1
    },
    {
      "id": 1,
      "text": "We're going to learn some commonly used prepositions today. ",
      "responseType": 1,
      "mediaUrl": "",
      "optionsCount": 1,
      "answers": [
        {
          "id": 1,
          "text": "Okay 😃",
          "answerType": 0,
          "nextBubbleId": 2,
          "score": 0,
          "isEntryPointForNewBot": false,
          "isEntryPointForNewTest": false,
          "questionsCount": 0,
          "filename": ""
        }
      ],
      "isEntryPointForNewTest": false,
      "questionsCount": 0,
      "filename": "",
      "nextBubbleId": 2,
      "delay": 3
    },
    {
      "id": 2,
      "text": "First, let's discuss what prepositions are.",
      "responseType": 1,
      "mediaUrl": "",
      "optionsCount": 1,
      "answers": [
        {
          "id": 2,
          "text": "Alright!",
          "answerType": 0,
          "nextBubbleId": 3,
          "score": 0,
          "isEntryPointForNewBot": false,
          "isEntryPointForNewTest": false,
          "questionsCount": 0,
          "filename": ""
        }
      ],
      "isEntryPointForNewTest": false,
      "questionsCount": 0,
      "filename": "",
      "nextBubbleId": 3,
      "delay": 1
    },
    {
      "id": 3,
      "text": "Prepositions are words that describe the relation between two or more words in a sentence.",
      "responseType": 0,
      "mediaUrl": "",
      "optionsCount": 0,
      "answers": [],
      "isEntryPointForNewTest": false,
      "questionsCount": 0,
      "filename": "",
      "nextBubbleId": 4,
      "delay": 1
    },
    {
      "id": 4,
      "text": "For example -<br>The book was <b>on</b> the table.<br>She is <b>at</b> the bar.<br>He will be here <b>in</b> an hour.<br>They are jumping <b>over</b> the wall.",
      "responseType": 1,
      "mediaUrl": "",
      "optionsCount": 1,
      "answers": [
        {
          "id": 4,
          "text": "Noted ✍️",
          "answerType": 0,
          "nextBubbleId": 5,
          "score": 0,
          "isEntryPointForNewBot": false,
          "isEntryPointForNewTest": false,
          "questionsCount": 0,
          "filename": ""
        }
      ],
      "isEntryPointForNewTest": false,
      "questionsCount": 0,
      "filename": "",
      "nextBubbleId": 5,
      "delay": 1
    },
    {
      "id": 5,
      "text": "Prepositions can help us understand where an object is.",
      "responseType": 0,
      "mediaUrl": "",
      "optionsCount": 0,
      "answers": [],
      "isEntryPointForNewTest": false,
      "questionsCount": 0,
      "filename": "",
      "nextBubbleId": 6,
      "delay": 1
    },
    {
      "id": 6,
      "text": "For example -<br><b>Where</b> is she? She is <b>at</b> the bar.",
      "responseType": 1,
      "mediaUrl": "",
      "optionsCount": 1,
      "answers": [
        {
          "id": 6,
          "text": "Got it 👍",
          "answerType": 0,
          "nextBubbleId": 7,
          "score": 0,
          "isEntryPointForNewBot": false,
          "isEntryPointForNewTest": false,
          "questionsCount": 0,
          "filename": ""
        }
      ],
      "isEntryPointForNewTest": false,
      "questionsCount": 0,
      "filename": "",
      "nextBubbleId": 7,
      "delay": 1
    },
    {
      "id": 7,
      "text": "Let's do a quick exercise to test your understanding!",
      "responseType": 1,
      "mediaUrl": "",
      "optionsCount": 1,
      "answers": [
        {
          "id": 7,
          "text": "Let's start 😃 ",
          "answerType": 0,
          "nextBubbleId": 0,
          "score": 0,
          "isEntryPointForNewBot": true,
          "isEntryPointForNewTest": false,
          "questionsCount": 0,
          "filename": "testbot_prepositions_on_at_01"
        }
      ],
      "isEntryPointForNewTest": false,
      "questionsCount": 0,
      "filename": "",
      "nextBubbleId": 8,
      "delay": 1
    },
    {
      "id": 8,
      "text": "Let's look at two prepositions in more detail. We'll start with <b>on</b>.",
      "responseType": 1,
      "mediaUrl": "",
      "optionsCount": 1,
      "answers": [
        {
          "id": 8,
          "text": "Okay 😃",
          "answerType": 0,
          "nextBubbleId": 9,
          "score": 0,
          "isEntryPointForNewBot": false,
          "isEntryPointForNewTest": false,
          "questionsCount": 0,
          "filename": ""
        }
      ],
      "isEntryPointForNewTest": false,
      "questionsCount": 0,
      "filename": "",
      "nextBubbleId": 9,
      "delay": 1
    },
    {
      "id": 9,
      "text": "<b>On</b> is used when an object is placed on a surface.",
      "responseType": 0,
      "mediaUrl": "",
      "optionsCount": 0,
      "isEntryPointForNewTest": false,
      "questionsCount": 0,
      "filename": "",
      "nextBubbleId": 10,
      "delay": 1
    },
    {
      "id": 10,
      "text": "For example -<br>Your glasses are <b>on</b> the desk.<br>He is walking <b>on</b> the footpath.",
      "responseType": 1,
      "mediaUrl": "",
      "optionsCount": 1,
      "answers": [
        {
          "id": 10,
          "text": "Okay 👍",
          "answerType": 0,
          "nextBubbleId": 11,
          "score": 0,
          "isEntryPointForNewBot": true,
          "isEntryPointForNewTest": false,
          "questionsCount": 0,
          "filename": "testbot_prepositions_on_at_01"
        }
      ],
      "isEntryPointForNewTest": false,
      "questionsCount": 0,
      "filename": "",
      "nextBubbleId": 11,
      "delay": 3
    },
    {
      "id": 11,
      "text": "<i>On</i> can be used as a preposition of time as well.",
      "responseType": 0,
      "mediaUrl": "",
      "optionsCount": 0,
      "answers": [],
      "isEntryPointForNewTest": false,
      "questionsCount": 0,
      "filename": "",
      "nextBubbleId": 12,
      "delay": 1
    },
    {
      "id": 12,
      "text": "On is used for <b>days</b> and <b>dates</b>.",
      "responseType": 1,
      "mediaUrl": "",
      "optionsCount": 1,
      "answers": [
        {
          "id": 12,
          "text": "Could you give me some examples?",
          "answerType": 0,
          "nextBubbleId": 13,
          "score": 0,
          "isEntryPointForNewBot": false,
          "isEntryPointForNewTest": false,
          "questionsCount": 0,
          "filename": ""
        }
      ],
      "isEntryPointForNewTest": false,
      "questionsCount": 0,
      "filename": "",
      "nextBubbleId": 13,
      "delay": 1
    },
    {
      "id": 13,
      "text": "Our next class is <b>on</b> Friday. (days)<br>His birthday is <b>on</b> 1st July. (dates)",
      "responseType": 1,
      "mediaUrl": "",
      "optionsCount": 1,
      "answers": [
        {
          "id": 13,
          "text": "Got it 😃 ",
          "answerType": 0,
          "nextBubbleId": 14,
          "score": 0,
          "isEntryPointForNewBot": true,
          "isEntryPointForNewTest": false,
          "questionsCount": 0,
          "filename": "testbot_prepositions_on_at_03"
        }
      ],
      "isEntryPointForNewTest": false,
      "questionsCount": 0,
      "filename": "",
      "nextBubbleId": 14,
      "delay": 1
    },
    {
      "id": 14,
      "text": "Are you ready to move on to the next preposition?",
      "responseType": 1,
      "mediaUrl": "",
      "optionsCount": 1,
      "answers": [
        {
          "id": 14,
          "text": "Sure! 👍",
          "answerType": 1,
          "nextBubbleId": 15,
          "score": 0,
          "isEntryPointForNewBot": false,
          "isEntryPointForNewTest": false,
          "questionsCount": 0,
          "filename": ""
        }
      ],
      "isEntryPointForNewTest": false,
      "questionsCount": 0,
      "filename": "",
      "nextBubbleId": 15,
      "delay": 1
    },
    {
      "id": 15,
      "text": "Awesome! The next preposition is <b>at</b>.",
      "responseType": 0,
      "mediaUrl": "",
      "optionsCount": 0,
      "answers": [],
      "isEntryPointForNewTest": false,
      "questionsCount": 0,
      "filename": "",
      "nextBubbleId": 16,
      "delay": 3
    },
    {
      "id": 16,
      "text": "<b>At</b> can be used for <b>places</b> and <b>time</b>.",
      "responseType": 0,
      "mediaUrl": "",
      "optionsCount": 0,
      "answers": [],
      "isEntryPointForNewTest": false,
      "questionsCount": 0,
      "filename": "",
      "nextBubbleId": 17,
      "delay": 3
    },
    {
      "id": 17,
      "text": "She was sitting <b>at</b> the table.<br>He was waiting <b>at</b> the cafe.<br>I will study <b>at</b> night.<br>They will be there <b>at</b> 8 pm.",
      "responseType": 1,
      "mediaUrl": "",
      "optionsCount": 1,
      "answers": [
        {
          "id": 17,
          "text": "Got it 👍",
          "answerType": 1,
          "nextBubbleId": 18,
          "score": 0,
          "isEntryPointForNewBot": true,
          "isEntryPointForNewTest": false,
          "questionsCount": 0,
          "filename": "testbot_prepositions_on_at_04"
        }
      ],
      "isEntryPointForNewTest": false,
      "questionsCount": 0,
      "filename": "",
      "nextBubbleId": 18,
      "delay": 1
    },
    {
      "id": 18,
      "text": "Let's revise.",
      "responseType": 1,
      "mediaUrl": "",
      "optionsCount": 0,
      "isEntryPointForNewTest": false,
      "questionsCount": 0,
      "filename": "",
      "nextBubbleId": 19,
      "delay": 1
    },
    {
      "id": 19,
      "text": "Let's look at the uses of at and on.",
      "responseType": 2,
      "mediaUrl": "on-at.png",
      "optionsCount": 1,
      "answers": [
        {
          "id": 19,
          "text": "Got it 👍",
          "answerType": 0,
          "nextBubbleId": 20,
          "score": 0,
          "isEntryPointForNewBot": false,
          "isEntryPointForNewTest": false,
          "questionsCount": 0,
          "filename": ""
        }
      ],
      "isEntryPointForNewTest": false,
      "questionsCount": 0,
      "filename": "",
      "nextBubbleId": 20,
      "delay": 1
    },
    {
      "id": 20,
      "text": "You've done very well! Keep it up!",
      "responseType": 0,
      "mediaUrl": "",
      "optionsCount": 0,
      "isEntryPointForNewTest": false,
      "questionsCount": 0,
      "filename": "",
      "nextBubbleId": 21,
      "delay": 2
    },
    {
      "id": 21,
      "text": "You can come back anytime for a quick revision.",
      "responseType": 0,
      "mediaUrl": "",
      "optionsCount": 0,
      "isEntryPointForNewTest": false,
      "questionsCount": 0,
      "filename": "",
      "nextBubbleId": -2,
      "delay": 1
    }
  ]
}